genapp.py
appgen/__init__.py
appgen/appgen.config.yaml
appgen/cli.py
appgen/config.py
appgen/framework_selector.py
appgen/project_manager.py
appgen/ui_helper.py
generator/generate.py
templates/astrojs/base/README.md
templates/astrojs/base/astro.config.mjs
templates/astrojs/base/package-lock.json
templates/astrojs/base/package.json
templates/astrojs/base/tsconfig.json
templates/astrojs/base/public/favicon.svg
templates/astrojs/base/src/assets/astro.svg
templates/astrojs/base/src/assets/background.svg
templates/astrojs/base/src/components/Welcome.astro
templates/astrojs/base/src/layouts/Layout.astro
templates/astrojs/base/src/pages/index.astro
templates/django/base/README.md
templates/django/base/manage.py
templates/django/base/requirements.txt
templates/django/base/project/__init__.py
templates/django/base/project/asgi.py
templates/django/base/project/settings.py
templates/django/base/project/urls.py
templates/django/base/project/wsgi.py
templates/express/base/package.json
templates/express/base/src/index.js
templates/express/mongodb/README.md
templates/express/mongodb/package.json
templates/express/mongodb/src/index.js
templates/express/postgresql/README.md
templates/express/postgresql/env.example
templates/express/postgresql/package.json
templates/express/postgresql/src/index.js
templates/express/supabase/README.md
templates/express/supabase/env.example
templates/express/supabase/package.json
templates/express/supabase/src/index.js
templates/express/typescript/package.json
templates/express/typescript/tsconfig.json
templates/express/typescript/src/index.ts
templates/flask/base/requirements.txt
templates/flask/base/run.py
templates/flask/base/app/main.py
templates/nextjs/app/next.config.js
templates/nextjs/app/package.json
templates/nextjs/app/app/layout.js
templates/nextjs/app/app/page.js
templates/nextjs/app/styles/globals.css
templates/nextjs/app-prisma/package.json
templates/nextjs/app-prisma/app/page.tsx
templates/nextjs/app-prisma/app/api/users/route.ts
appgen-0.3.3.dist-info/METADATA
appgen-0.3.3.dist-info/WHEEL
appgen-0.3.3.dist-info/entry_points.txt
appgen-0.3.3.dist-info/top_level.txt
appgen-0.3.3.dist-info/RECORD
